{"P3": {"labels": ["duplicate", "duomacc"], "postTitle": "\u3010\u591a\u8bed\u8a00\u4effOKX\u4ea4\u6613\u6240\u3011DAPP+\u79d2\u5408\u7ea6\u4ea4\u6613\u6240+\u8d28\u62bc\u7533\u8d2d", "postUrl": "post/%E3%80%90-duo-yu-yan-fang-OKX-jiao-yi-suo-%E3%80%91DAPP%2B-miao-he-yue-jiao-yi-suo-%2B-zhi-ya-shen-gou.html", "createdDate": "2024-12-29", "dateLabelColor": "#bc4c00"}, "P1": {"labels": ["duomacc"], "postTitle": "\u591a\u7801\u7f51-\u6211\u4eec\u6c47\u805a\u5176\u5b83\u8bba\u575b\u8d44\u6e90\u548c\u4e00\u624b\u72ec\u5bb6\u8d44\u6e90\uff0c\u575a\u6301\u6bcf\u5929\u66f4\u65b0\u8d44\u6e90\u7edd\u4e0d\u505c\u6b62\uff01", "postUrl": "post/duo-ma-wang---wo-men-hui-ju-qi-ta-lun-tan-zi-yuan-he-yi-shou-du-jia-zi-yuan-%EF%BC%8C-jian-chi-mei-tian-geng-xin-zi-yuan-jue-bu-ting-zhi-%EF%BC%81.html", "createdDate": "2024-11-05", "dateLabelColor": "#bc4c00"}, "labelColorDict": {"bug": "#d73a4a", "documentation": "#0075ca", "duomacc": "#0E8A16", "duplicate": "#cfd3d7", "enhancement": "#a2eeef", "good first issue": "#7057ff", "help wanted": "#008672", "invalid": "#e4e669", "question": "#d876e3", "wontfix": "#ffffff"}}